{
    "check_box": {
        "next": 1630355549,
        "param": {
            "track": true,
            "resize": 0.25
        }
    },
    "heal_500": {
        "next": 1630355575,
        "param": {
            "track": true,
            "resize": 0.25,
            "max_to_heal": 500
        },
        "func": "heal_max"
    },
    "sheltering": {
        "next": 1630356786,
        "param": {
            "track": true,
            "resize": 0.25,
            "reset_threshold": 8
        }
    },
    "trade": {
        "next": 1630338132,
        "param": {
            "track": true,
            "resize": 0.25
        }
    },
    "get_amethyst": {
        "next": 1630341804,
        "param": {
            "track": true,
            "resize": 0.3
        }
    },
    "get_dragonforged": {
        "next": 1630341872,
        "param": {
            "track": true,
            "resize": 0.3
        }
    },
    "get_vip_shop": {
        "next": 1630341946,
        "param": {
            "track": true,
            "resize": 0.3
        }
    },
    "training_ground": {
        "next": 1630339615,
        "param": {
            "track": true,
            "resize": 0.25
        }
    },
    "explore_drag": {
        "next": 1630340000,
        "param": {
            "track": true,
            "resize": 0.25,
            "hours": 1,
            "buy": 0,
            "dragon_id": 0
        }
    },
    "daily_msg": {
        "next": 1630342876,
        "param": {
            "track": true,
            "resize": 0.25
        }
    },
    "sell_quick_box": {
        "next": 1630341133,
        "param": {
            "track": true,
            "resize": 0.25,
            "min_level": 5
        }
    },
    "complete_all_trials": {
        "next": 1630305829,
        "param": {
            "track": true,
            "resize": 0.25
        }
    },
    "get_salary": {
        "next": 1630305935,
        "param": {
            "track": true,
            "resize": 0.25
        }
    },
    "get_bonus": {
        "next": 1630305964,
        "param": {
            "track": true,
            "resize": 0.25
        }
    },
    "get_knight": {
        "next": 1630306092,
        "param": {
            "track": true,
            "resize": 0.25
        }
    },
    "get_list": {
        "next": 1630306126,
        "param": {
            "track": true,
            "resize": 0.25,
            "items": [
                "vip",
                "amethyst",
                "dragon"
            ]
        }
    }
}