{
    "check_box": {
        "next": 1629058905,
        "param": {
            "track": true,
            "resize": 0.25
        }
    },
    "bank_claim": {
        "next": 1626674962,
        "param": {
            "track": true,
            "resize": 0.25
        }
    },
    "heal_500": {
        "next": 1629058325,
        "param": {
            "track": true,
            "resize": 0.25,
            "max_to_heal": 500
        },
        "func": "heal_max"
    },
    "sheltering": {
        "next": 1629072945,
        "param": {
            "track": true,
            "resize": 0.25,
            "reset_threshold": 8
        }
    },
    "trade": {
        "next": 1629058778,
        "param": {
            "track": true,
            "resize": 0.25
        }
    },
    "get_amethyst": {
        "next": 1629062402,
        "param": {
            "track": true,
            "resize": 0.3
        }
    },
    "get_dragonforged": {
        "next": 1629062506,
        "param": {
            "track": true,
            "resize": 0.3
        }
    },
    "get_vip_shop": {
        "next": 1629062574,
        "param": {
            "track": true,
            "resize": 0.3
        }
    },
    "soldiers": {
        "cav": 500,
        "inf": 500,
        "spe": 500,
        "bow": 500
    },
    "train_mil": {
        "next": 1629056996,
        "param": {
            "track": true,
            "resize": 0.25,
            "level": 1,
            "soldiers": {
                "cav": 500,
                "inf": 500,
                "spe": 500,
                "bow": 500
            }
        }
    },
    "explore_drag": {
        "next": 1629057181,
        "param": {
            "track": true,
            "resize": 0.25,
            "hours": 1,
            "buy": 0,
            "dragon_id": 0
        }
    },
    "complete_all_trials": {
        "next": 1629004402,
        "param": {
            "track": true,
            "resize": 0.25
        }
    },
    "get_salary": {
        "next": 1629004405,
        "param": {
            "track": true,
            "resize": 0.25
        }
    },
    "get_bonus": {
        "next": 1629004407,
        "param": {
            "track": true,
            "resize": 0.25
        }
    },
    "get_knight": {
        "next": 1629004410,
        "param": {
            "track": true,
            "resize": 0.25
        }
    },
    "get_list": {
        "next": 1629004413,
        "param": {
            "track": true,
            "resize": 0.25,
            "items": [
                "vip",
                "amethyst",
                "dragon"
            ]
        }
    },
    "daily_msg": {
        "next": 1629118610,
        "param": {
            "track": true,
            "resize": 0.25
        }
    },
    "continue_bub": {
        "next": 1625523558,
        "param": {
            "track": true,
            "resize": 0.25
        }
    },
    "training_ground": {
        "next": 1629060237,
        "param": {
            "track": true,
            "resize": 0.25
        }
    },
    "sell_quick_box": {
        "next": 1629068403,
        "param": {
            "track": true,
            "resize": 0.25,
            "min_level": 5
        }
    }
}