{
    "check_box": {
        "next": 1627867086,
        "param": {
            "track": true,
            "resize": 0.25
        }
    },
    "bank_claim": {
        "next": 1626676582,
        "param": {
            "track": true,
            "resize": 0.25
        }
    },
    "heal_100": {
        "next": 1625238580,
        "param": {
            "track": true,
            "resize": 0.25,
            "max_to_heal": 100
        },
        "func": "heal_max"
    },
    "sheltering": {
        "next": 1627881472,
        "param": {
            "track": true,
            "resize": 0.25,
            "reset_threshold": 8
        }
    },
    "trade": {
        "next": 1627867240,
        "param": {
            "track": true,
            "resize": 0.25
        }
    },
    "get_amethyst": {
        "next": 1627870855,
        "param": {
            "track": true,
            "resize": 0.3
        }
    },
    "get_dragonforged": {
        "next": 1627852932,
        "param": {
            "track": true,
            "resize": 0.3
        }
    },
    "get_vip_shop": {
        "next": 1627852999,
        "param": {
            "track": true,
            "resize": 0.3
        }
    },
    "complete_all_trials": {
        "next": 1627798675,
        "param": {
            "track": true,
            "resize": 0.25
        }
    },
    "get_salary": {
        "next": 1627795081,
        "param": {
            "track": true,
            "resize": 0.25
        }
    },
    "get_bonus": {
        "next": 1627795083,
        "param": {
            "track": true,
            "resize": 0.25
        }
    },
    "get_knight": {
        "next": 1627795085,
        "param": {
            "track": true,
            "resize": 0.25
        }
    },
    "get_list": {
        "next": 1627798715,
        "param": {
            "track": true,
            "resize": 0.25,
            "items": [
                "vip",
                "amethyst",
                "dragon"
            ]
        }
    },
    "soldiers": {
        "cav": 500,
        "inf": 500,
        "spe": 500,
        "bow": 500
    },
    "train_mil": {
        "next": 1627853235,
        "param": {
            "track": true,
            "resize": 0.25,
            "level": 1,
            "soldiers": {
                "cav": 500,
                "inf": 500,
                "spe": 500,
                "bow": 500
            }
        }
    },
    "explore_drag": {
        "next": 1627853423,
        "param": {
            "track": true,
            "resize": 0.25,
            "hours": 1,
            "buy": 0,
            "dragon_id": 0
        }
    },
    "heal_500": {
        "next": 1627866877,
        "param": {
            "track": true,
            "resize": 0.25,
            "max_to_heal": 500
        },
        "func": "heal_max"
    },
    "daily_msg": {
        "next": 1627914872,
        "param": {
            "track": true,
            "resize": 0.25
        }
    },
    "continue_bub": {
        "next": 1625540916,
        "param": {
            "track": true,
            "resize": 0.25
        }
    },
    "training_ground": {
        "next": 1627850662,
        "param": {
            "track": true,
            "resize": 0.25
        }
    },
    "sell_quick_box": {
        "next": 1627853873,
        "param": {
            "track": true,
            "resize": 0.25,
            "min_level": 5
        }
    }
}