{
    "check_box": {
        "next": 1657312131,
        "local": "07/08/2022 14:28:51"
    },
    "enter_code": {
        "next": 1657308796,
        "local": "07/08/2022 13:33:16"
    },
    "explore_drag": {
        "next": 1657308443,
        "local": "07/08/2022 13:27:23"
    },
    "get_vip_box": {
        "next": 1657329599,
        "local": "07/08/2022 19:19:59"
    },
    "get_active_award": {
        "next": 1657308879,
        "local": "07/08/2022 13:34:39"
    },
    "get_salary": {
        "next": 1657325402,
        "local": "07/08/2022 18:10:02"
    },
    "get_bonus": {
        "next": 1657325402,
        "local": "07/08/2022 18:10:02"
    },
    "get_knight": {
        "next": 1657325399,
        "local": "07/08/2022 18:09:59"
    },
    "get_alli_quest": {
        "next": 1657312271,
        "local": "07/08/2022 14:31:11"
    },
    "auto_transport_rss": {
        "next": 1657308557,
        "local": "07/08/2022 13:29:17"
    },
    "get_alliance_chests": {
        "next": 1657313725,
        "local": "07/08/2022 14:55:25"
    },
    "get_amethyst": {
        "next": 1657329599,
        "local": "07/08/2022 19:19:59"
    },
    "get_discount": {
        "next": 1657328684,
        "local": "07/08/2022 19:04:44"
    },
    "bliz_elite_trial": {
        "next": 1657308591,
        "local": "07/08/2022 13:29:51"
    },
    "daily_msg": {
        "next": 1657309377,
        "local": "07/08/2022 13:42:57"
    },
    "upgrade_commanders": {
        "next": 1657311330,
        "local": "07/08/2022 14:15:30"
    },
    "sell_quick_box": {
        "next": 1657334308,
        "local": "07/08/2022 20:38:28"
    },
    "trade": {
        "next": 1657325747,
        "local": "07/08/2022 18:15:47"
    },
    "get_taven": {
        "next": 1657308692,
        "local": "07/08/2022 13:31:32"
    },
    "expeditions": {
        "next": 1657309114,
        "local": "07/08/2022 13:38:34"
    },
    "training_ground": {
        "next": 1657342752,
        "local": "07/08/2022 22:59:12"
    },
    "daily_train": {
        "log_unfinished": {
            "cav": [
                1,
                500
            ],
            "spe": [
                1,
                500
            ],
            "bow": [
                1,
                500
            ]
        },
        "log_reset_date": {
            "reset": "2022-07-08"
        },
        "next": 1657309125,
        "local": "07/08/2022 13:38:45"
    },
    "keep_lead": {
        "next": 1657309498,
        "local": "07/08/2022 13:44:58"
    },
    "at_groups": {
        "next": 1657311011,
        "local": "07/08/2022 14:10:11"
    },
    "bank_claim": {
        "next": 1657876553,
        "local": "07/15/2022 03:15:53"
    },
    "daily_farms": {
        "finished": [
            "grain",
            "lumb",
            "quar",
            "mint"
        ],
        "next": 1657308743,
        "local": "07/08/2022 13:32:23"
    },
    "balanced_farms": {
        "next": 1657308951,
        "local": "07/08/2022 13:35:51"
    }
}