{
    "check_box": {
        "next": 1657992978,
        "local": "07/16/2022 11:36:18"
    },
    "enter_code": {
        "next": 1657992454,
        "local": "07/16/2022 11:27:34"
    },
    "explore_drag": {
        "next": 1657992339,
        "local": "07/16/2022 11:25:39"
    },
    "get_vip_box": {
        "next": 1658020799,
        "local": "07/16/2022 19:19:59"
    },
    "get_active_award": {
        "next": 1657991240,
        "local": "07/16/2022 11:07:20"
    },
    "get_salary": {
        "next": 1658016603,
        "local": "07/16/2022 18:10:03"
    },
    "get_bonus": {
        "next": 1658016602,
        "local": "07/16/2022 18:10:02"
    },
    "get_knight": {
        "next": 1658016599,
        "local": "07/16/2022 18:09:59"
    },
    "get_alli_quest": {
        "next": 1658002475,
        "local": "07/16/2022 14:14:35"
    },
    "auto_transport_rss": {
        "next": 1657992053,
        "local": "07/16/2022 11:20:53"
    },
    "get_alliance_chests": {
        "next": 1657996638,
        "local": "07/16/2022 12:37:18"
    },
    "get_amethyst": {
        "next": 1657992164,
        "local": "07/16/2022 11:22:44"
    },
    "get_discount": {
        "next": 1657992238,
        "local": "07/16/2022 11:23:58"
    },
    "bliz_elite_trial": {
        "next": 1658033728,
        "local": "07/16/2022 22:55:28"
    },
    "daily_msg": {
        "next": 1658007198,
        "local": "07/16/2022 15:33:18"
    },
    "upgrade_commanders": {
        "next": 1657994944,
        "local": "07/16/2022 12:09:04"
    },
    "sell_quick_box": {
        "next": 1658027332,
        "local": "07/16/2022 21:08:52"
    },
    "trade": {
        "next": 1657995273,
        "local": "07/16/2022 12:14:33"
    },
    "get_taven": {
        "next": 1657992270,
        "local": "07/16/2022 11:24:30"
    },
    "expeditions": {
        "next": 1657992362,
        "local": "07/16/2022 11:26:02"
    },
    "training_ground": {
        "next": 1657999563,
        "local": "07/16/2022 13:26:03"
    },
    "daily_train": {
        "log_unfinished": {
            "cav": [
                1,
                500
            ],
            "spe": [
                1,
                500
            ],
            "bow": [
                1,
                500
            ]
        },
        "log_reset_date": {
            "reset": "2022-07-16"
        },
        "next": 1657990936,
        "local": "07/16/2022 11:02:16"
    },
    "keep_lead": {
        "next": 1657991815,
        "local": "07/16/2022 11:16:55"
    },
    "at_groups": {
        "next": 1657993065,
        "local": "07/16/2022 11:37:45"
    },
    "bank_claim": {
        "next": 1658486225,
        "local": "07/22/2022 04:37:05"
    },
    "daily_farms": {
        "finished": [
            "grain",
            "lumb",
            "quar",
            "mint"
        ],
        "next": 1657990835,
        "local": "07/16/2022 11:00:35"
    },
    "balanced_farms": {
        "next": 1657990973,
        "local": "07/16/2022 11:02:53"
    }
}