{
    "continue_bub": {
        "next": 1650963853,
        "local": "04/26/2022 03:04:13"
    },
    "check_box": {
        "next": 1650964001,
        "local": "04/26/2022 03:06:41"
    },
    "complete_all_trials": {
        "next": 1651018212,
        "local": "04/26/2022 18:10:12"
    },
    "explore_drag": {
        "next": 1650963306,
        "local": "04/26/2022 02:55:06"
    },
    "get_vip_box": {
        "next": 1650963335,
        "local": "04/26/2022 02:55:35"
    },
    "get_active_award": {
        "next": 1650963403,
        "local": "04/26/2022 02:56:43"
    },
    "get_alli_quest": {
        "next": 1650963428,
        "local": "04/26/2022 02:57:08"
    },
    "auto_transport_rss": {
        "next": 1650963489,
        "local": "04/26/2022 02:58:09"
    },
    "get_alliance_chests": {
        "next": 1650964081,
        "local": "04/26/2022 03:08:01"
    },
    "get_discount": {
        "next": 1650963522,
        "local": "04/26/2022 02:58:42"
    },
    "daily_msg": {
        "next": 1650984131,
        "local": "04/26/2022 08:42:11"
    },
    "upgrade_commanders": {
        "next": 1650966287,
        "local": "04/26/2022 03:44:47"
    },
    "sell_quick_box": {
        "next": 1651000349,
        "local": "04/26/2022 13:12:29"
    },
    "trade": {
        "next": 1650963206,
        "local": "04/26/2022 02:53:26"
    },
    "get_taven": {
        "next": 1650963621,
        "local": "04/26/2022 03:00:21"
    },
    "expeditions": {
        "next": 1650963706,
        "local": "04/26/2022 03:01:46"
    },
    "training_ground": {
        "next": 1650963791,
        "local": "04/26/2022 03:03:11"
    },
    "at_groups": {
        "next": 1650966780,
        "local": "04/26/2022 03:53:00"
    },
    "daily_farms": {
        "finished": [
            "grain",
            "mint",
            "quar",
            "lumb"
        ],
        "next": 1650959421,
        "local": "04/26/2022 01:50:21"
    },
    "bank_claim": {
        "next": 1650958251,
        "local": "04/26/2022 01:30:51"
    },
    "keep_lead": {
        "next": 1650963918,
        "local": "04/26/2022 03:05:18"
    },
    "daily_train": {
        "next": 1651017650,
        "local": "04/26/2022 18:00:50"
    }
}