{
    "continue_bub": {
        "next": 1649663944,
        "local": "04/11/2022 01:59:04"
    },
    "daily_msg": {
        "next": 1649680426,
        "local": "04/11/2022 06:33:46"
    },
    "get_active_award": {
        "next": 1649661714,
        "local": "04/11/2022 01:21:54"
    },
    "train_mil": {
        "next": 1649655018,
        "local": "04/10/2022 23:30:18"
    },
    "complete_all_trials": {
        "next": 1649661013,
        "local": "04/11/2022 01:10:13"
    },
    "check_box": {
        "next": 1649661358,
        "local": "04/11/2022 01:15:58"
    },
    "explore_drag": {
        "next": 1649662373,
        "local": "04/11/2022 01:32:53"
    },
    "get_vip_box": {
        "next": 1649726399,
        "local": "04/11/2022 19:19:59"
    },
    "get_alli_quest": {
        "next": 1649660352,
        "local": "04/11/2022 00:59:12"
    },
    "auto_transport_rss": {
        "next": 1649660403,
        "local": "04/11/2022 01:00:03"
    },
    "get_alliance_chests": {
        "next": 1649666901,
        "local": "04/11/2022 02:48:21"
    },
    "get_discount": {
        "next": 1649724783,
        "local": "04/11/2022 18:53:03"
    },
    "upgrade_commanders": {
        "next": 1649663652,
        "local": "04/11/2022 01:54:12"
    },
    "sell_quick_box": {
        "next": 1649669417,
        "local": "04/11/2022 03:30:17"
    },
    "trade": {
        "next": 1649667641,
        "local": "04/11/2022 03:00:41"
    },
    "get_taven": {
        "next": 1649661180,
        "local": "04/11/2022 01:13:00"
    },
    "expeditions": {
        "next": 1649661425,
        "local": "04/11/2022 01:17:05"
    },
    "training_ground": {
        "next": 1649685811,
        "local": "04/11/2022 08:03:31"
    },
    "schedule_leader": {
        "next": 1649657141,
        "local": "04/11/2022 00:05:41"
    },
    "at_groups": {
        "next": 1649658891,
        "local": "04/11/2022 00:34:51"
    },
    "daily_farms": {
        "finished": [
            "grain",
            "mint",
            "quar",
            "lumb",
            "mine"
        ],
        "next": 1649724647,
        "local": "04/11/2022 18:50:47"
    }
}