{
    "continue_bub": {
        "next": 1651072041,
        "local": "04/27/2022 09:07:21"
    },
    "daily_msg": {
        "next": 1651052189,
        "local": "04/27/2022 03:36:29"
    },
    "get_active_award": {
        "next": 1651051237,
        "local": "04/27/2022 03:20:37"
    },
    "complete_all_trials": {
        "next": 1651051111,
        "local": "04/27/2022 03:18:31"
    },
    "check_box": {
        "next": 1651056716,
        "local": "04/27/2022 04:51:56"
    },
    "explore_drag": {
        "next": 1651051778,
        "local": "04/27/2022 03:29:38"
    },
    "get_vip_box": {
        "next": 1651108799,
        "local": "04/27/2022 19:19:59"
    },
    "get_alli_quest": {
        "next": 1651069146,
        "local": "04/27/2022 08:19:06"
    },
    "auto_transport_rss": {
        "next": 1651051530,
        "local": "04/27/2022 03:25:30"
    },
    "get_alliance_chests": {
        "next": 1651057909,
        "local": "04/27/2022 05:11:49"
    },
    "get_discount": {
        "next": 1651051693,
        "local": "04/27/2022 03:28:13"
    },
    "upgrade_commanders": {
        "next": 1651052370,
        "local": "04/27/2022 03:39:30"
    },
    "sell_quick_box": {
        "next": 1651060347,
        "local": "04/27/2022 05:52:27"
    },
    "trade": {
        "next": 1651090986,
        "local": "04/27/2022 14:23:06"
    },
    "get_taven": {
        "next": 1651051733,
        "local": "04/27/2022 03:28:53"
    },
    "expeditions": {
        "next": 1651069011,
        "local": "04/27/2022 08:16:51"
    },
    "training_ground": {
        "next": 1651092210,
        "local": "04/27/2022 14:43:30"
    },
    "at_groups": {
        "next": 1651052820,
        "local": "04/27/2022 03:47:00"
    },
    "daily_farms": {
        "finished": [
            "mine",
            "grain",
            "lumb",
            "mint",
            "quar"
        ],
        "next": 1651107674,
        "local": "04/27/2022 19:01:14"
    },
    "keep_lead": {
        "next": 1651052036,
        "local": "04/27/2022 03:33:56"
    },
    "daily_train": {
        "next": 1651104005,
        "local": "04/27/2022 18:00:05"
    }
}