{
    "continue_bub": {
        "next": 1650992118,
        "local": "04/26/2022 10:55:18"
    },
    "daily_msg": {
        "next": 1651009643,
        "local": "04/26/2022 15:47:23"
    },
    "get_active_award": {
        "next": 1650992338,
        "local": "04/26/2022 10:58:58"
    },
    "complete_all_trials": {
        "next": 1650993459,
        "local": "04/26/2022 11:17:39"
    },
    "check_box": {
        "next": 1650992215,
        "local": "04/26/2022 10:56:55"
    },
    "explore_drag": {
        "next": 1650994602,
        "local": "04/26/2022 11:36:42"
    },
    "get_vip_box": {
        "next": 1651022399,
        "local": "04/26/2022 19:19:59"
    },
    "get_alli_quest": {
        "next": 1651001080,
        "local": "04/26/2022 13:24:40"
    },
    "auto_transport_rss": {
        "next": 1650993206,
        "local": "04/26/2022 11:13:26"
    },
    "get_alliance_chests": {
        "next": 1650999905,
        "local": "04/26/2022 13:05:05"
    },
    "get_discount": {
        "next": 1651035526,
        "local": "04/26/2022 22:58:46"
    },
    "upgrade_commanders": {
        "next": 1650987581,
        "local": "04/26/2022 09:39:41"
    },
    "sell_quick_box": {
        "next": 1650994872,
        "local": "04/26/2022 11:41:12"
    },
    "trade": {
        "next": 1651005253,
        "local": "04/26/2022 14:34:13"
    },
    "get_taven": {
        "next": 1650986475,
        "local": "04/26/2022 09:21:15"
    },
    "expeditions": {
        "next": 1650986699,
        "local": "04/26/2022 09:24:59"
    },
    "training_ground": {
        "next": 1650995119,
        "local": "04/26/2022 11:45:19"
    },
    "at_groups": {
        "next": 1650987944,
        "local": "04/26/2022 09:45:44"
    },
    "daily_farms": {
        "finished": [
            "mint",
            "mine",
            "grain",
            "lumb",
            "quar"
        ],
        "next": 1651020494,
        "local": "04/26/2022 18:48:14"
    },
    "keep_lead": {
        "next": 1650986710,
        "local": "04/26/2022 09:25:10"
    },
    "daily_train": {
        "next": 1651017615,
        "local": "04/26/2022 18:00:15"
    }
}