{
    "continue_bub": {
        "next": 1651242666,
        "local": "04/29/2022 08:31:06"
    },
    "daily_msg": {
        "next": 1651225197,
        "local": "04/29/2022 03:39:57"
    },
    "get_active_award": {
        "next": 1651224440,
        "local": "04/29/2022 03:27:20"
    },
    "complete_all_trials": {
        "next": 1651223877,
        "local": "04/29/2022 03:17:57"
    },
    "check_box": {
        "next": 1651225334,
        "local": "04/29/2022 03:42:14"
    },
    "explore_drag": {
        "next": 1651225174,
        "local": "04/29/2022 03:39:34"
    },
    "get_vip_box": {
        "next": 1651281599,
        "local": "04/29/2022 19:19:59"
    },
    "get_alli_quest": {
        "next": 1651230614,
        "local": "04/29/2022 05:10:14"
    },
    "auto_transport_rss": {
        "next": 1651223078,
        "local": "04/29/2022 03:04:38"
    },
    "get_alliance_chests": {
        "next": 1651224345,
        "local": "04/29/2022 03:25:45"
    },
    "get_discount": {
        "next": 1651223188,
        "local": "04/29/2022 03:06:28"
    },
    "upgrade_commanders": {
        "next": 1651226243,
        "local": "04/29/2022 03:57:23"
    },
    "sell_quick_box": {
        "next": 1651259114,
        "local": "04/29/2022 13:05:14"
    },
    "trade": {
        "next": 1651225174,
        "local": "04/29/2022 03:39:34"
    },
    "get_taven": {
        "next": 1651223642,
        "local": "04/29/2022 03:14:02"
    },
    "expeditions": {
        "next": 1651250846,
        "local": "04/29/2022 10:47:26"
    },
    "training_ground": {
        "next": 1651253227,
        "local": "04/29/2022 11:27:07"
    },
    "at_groups": {
        "next": 1651227066,
        "local": "04/29/2022 04:11:06"
    },
    "daily_farms": {
        "finished": [
            "lumb",
            "quar",
            "mine",
            "grain",
            "mint"
        ],
        "next": 1651181292,
        "local": "04/28/2022 15:28:12"
    },
    "keep_lead": {
        "next": 1651224027,
        "local": "04/29/2022 03:20:27"
    },
    "daily_train": {
        "next": 1651276839,
        "local": "04/29/2022 18:00:39"
    }
}